bears/FileMetadata.py
bears/__init__.py
bears/asset.py
bears/document.py
bears/constants/_DataProcessingConstants.py
bears/constants/_FileConstants.py
bears/constants/_MLTypeConstants.py
bears/constants/__init__.py
bears/core/frame/DaskScalableDataFrame.py
bears/core/frame/DaskScalableSeries.py
bears/core/frame/DatumScalableSeries.py
bears/core/frame/DictScalableDataFrame.py
bears/core/frame/ListOfDictScalableDataFrame.py
bears/core/frame/NumpyArrayScalableSeries.py
bears/core/frame/NumpyRecordArrayScalableDataFrame.py
bears/core/frame/PandasScalableDataFrame.py
bears/core/frame/PandasScalableSeries.py
bears/core/frame/RecordScalableDataFrame.py
bears/core/frame/ScalableDataFrame.py
bears/core/frame/ScalableDataFrameDataset.py
bears/core/frame/ScalableSeries.py
bears/core/frame/TensorScalableSeries.py
bears/core/frame/TorchScalableSeries.py
bears/core/frame/__init__.py
bears/processor/_DataPipeline.py
bears/processor/_DataProcessor.py
bears/processor/_DataProcessor_mixins.py
bears/processor/_Nto1ColumnProcessor.py
bears/processor/_SingleColumnProcessor.py
bears/processor/__init__.py
bears/processor/_categorical/_CategoricalMissingValueImputation.py
bears/processor/_categorical/_LabelAffix.py
bears/processor/_categorical/_LabelEncoding.py
bears/processor/_categorical/__init__.py
bears/processor/_numeric/_NumericMissingValueImputation.py
bears/processor/_numeric/__init__.py
bears/processor/_text/_CaseTransformation.py
bears/processor/_text/_HtmlTagRemoval.py
bears/processor/_text/_PunctuationCleaner.py
bears/processor/_text/_RegexSubstitution.py
bears/processor/_text/_StringRemoval.py
bears/processor/_text/_TFIDFVectorization.py
bears/processor/_text/_TextConcatenation.py
bears/processor/_text/__init__.py
bears/processor/_vector/_VectorAssembler.py
bears/processor/_vector/_VectorDensifier.py
bears/processor/_vector/__init__.py
bears/reader/Reader.py
bears/reader/__init__.py
bears/reader/asset/AssetReader.py
bears/reader/asset/__init__.py
bears-0.1.6.dist-info/METADATA
bears-0.1.6.dist-info/WHEEL
bears-0.1.6.dist-info/licenses/LICENSE
bears-0.1.6.dist-info/RECORD
